emr_launcher_consul/__init__.py
emr_launcher_consul-1.2.1.dist-info/DESCRIPTION.rst
emr_launcher_consul-1.2.1.dist-info/METADATA
emr_launcher_consul-1.2.1.dist-info/RECORD
emr_launcher_consul-1.2.1.dist-info/WHEEL
emr_launcher_consul-1.2.1.dist-info/metadata.json
emr_launcher_consul-1.2.1.dist-info/top_level.txt
